LICENCE
README.md
setup.py
tools_kit.egg-info/PKG-INFO
tools_kit.egg-info/SOURCES.txt
tools_kit.egg-info/dependency_links.txt
tools_kit.egg-info/requires.txt
tools_kit.egg-info/top_level.txt
tools_rest/__init__.py
tools_rest/constants_exc.py
tools_rest/exceptions.py
tools_rest/response_view.py
tools_rest/statuscode.py
tools_rest/swagger_view.py