Metadata-Version: 2.1
Name: tools-kit
Version: 0.2.0
Summary: Gerenciador para facilitar o desenvolvimento padronizado
Author: Mateus Laurentino de Andrade
Author-email: mateus_laurentino@outlook.com
License: MIT License
Keywords: tools kit
License-File: LICENCE
Requires-Dist: django
Requires-Dist: djangorestframework
